sphinx_autodoc_typehints/__init__.py
sphinx_autodoc_typehints/_parser.py
sphinx_autodoc_typehints/attributes_patch.py
sphinx_autodoc_typehints/patches.py
sphinx_autodoc_typehints/py.typed
sphinx_autodoc_typehints/version.py
sphinx_autodoc_typehints-3.6.0.dist-info/METADATA
sphinx_autodoc_typehints-3.6.0.dist-info/WHEEL
sphinx_autodoc_typehints-3.6.0.dist-info/licenses/LICENSE
sphinx_autodoc_typehints-3.6.0.dist-info/RECORD
