Metadata-Version: 2.4
Name: sphinx-autodoc-typehints
Version: 3.6.0
Summary: Type hints (PEP 484) support for the Sphinx autodoc extension
Project-URL: Changelog, https://github.com/tox-dev/sphinx-autodoc-typehints/releases
Project-URL: Homepage, https://github.com/tox-dev/sphinx-autodoc-typehints
Project-URL: Source, https://github.com/tox-dev/sphinx-autodoc-typehints
Project-URL: Tracker, https://github.com/tox-dev/sphinx-autodoc-typehints/issues
Author-email: Bernát Gábor <gaborjbernat@gmail.com>
Maintainer-email: Bernát Gábor <gaborjbernat@gmail.com>
License-Expression: MIT
License-File: LICENSE
Keywords: environments,isolated,testing,virtual
Classifier: Development Status :: 5 - Production/Stable
Classifier: Framework :: Sphinx :: Extension
Classifier: Intended Audience :: Developers
Classifier: License :: OSI Approved :: MIT License
Classifier: Programming Language :: Python
Classifier: Programming Language :: Python :: 3 :: Only
Classifier: Programming Language :: Python :: 3.11
Classifier: Programming Language :: Python :: 3.12
Classifier: Programming Language :: Python :: 3.13
Classifier: Programming Language :: Python :: 3.14
Classifier: Topic :: Documentation :: Sphinx
Requires-Python: >=3.11
Requires-Dist: sphinx>=9.0.4
Provides-Extra: docs
Requires-Dist: furo>=2025.9.25; extra == 'docs'
Provides-Extra: testing
Requires-Dist: covdefaults>=2.3; extra == 'testing'
Requires-Dist: coverage>=7.13; extra == 'testing'
Requires-Dist: defusedxml>=0.7.1; extra == 'testing'
Requires-Dist: diff-cover>=9.7.2; extra == 'testing'
Requires-Dist: pytest-cov>=7; extra == 'testing'
Requires-Dist: pytest>=9.0.2; extra == 'testing'
Requires-Dist: sphobjinv>=2.3.1.3; extra == 'testing'
Requires-Dist: typing-extensions>=4.15; extra == 'testing'
